[
    {
        "featureType": "all",
        "elementType": "all",
        "stylers": [
            {
                "visibility": "on"
            }
        ]
    },
    {
        "featureType": "all",
        "elementType": "labels.text",
        "stylers": [
            {
                "color": "#ffffff"
            }
        ]
    },
    {
        "featureType": "all",
        "elementType": "labels.text.stroke",
        "stylers": [
            {
                "color": "#d6e9ce"
            }
        ]
    },
    {
        "featureType": "administrative",
        "elementType": "geometry",
        "stylers": [
            {
                "visibility": "off"
            }
        ]
    },
    {
        "featureType": "administrative.country",
        "elementType": "labels.text.stroke",
        "stylers": [
            {
                "visibility": "off"
            },
            {
                "color": "#6b5252"
            }
        ]
    },
    {
        "featureType": "administrative.province",
        "elementType": "labels.text.stroke",
        "stylers": [
            {
                "visibility": "off"
            }
        ]
    },
    {
        "featureType": "administrative.locality",
        "elementType": "labels.text.stroke",
        "stylers": [
            {
                "visibility": "on"
            },
            {
                "color": "#7d9778"
            }
        ]
    },
    {
        "featureType": "administrative.neighborhood",
        "elementType": "labels.text.stroke",
        "stylers": [
            {
                "visibility": "off"
            }
        ]
    },
    {
        "featureType": "administrative.land_parcel",
        "elementType": "labels.text.stroke",
        "stylers": [
            {
                "visibility": "off"
            }
        ]
    },
    {
        "featureType": "landscape",
        "elementType": "all",
        "stylers": [
            {
                "visibility": "on"
            }
        ]
    },
    {
        "featureType": "landscape",
        "elementType": "geometry",
        "stylers": [
            {
                "saturation": "-5"
            },
            {
                "lightness": "-1"
            },
            {
                "visibility": "off"
            }
        ]
    },
    {
        "featureType": "landscape.man_made",
        "elementType": "geometry.fill",
        "stylers": [
            {
                "visibility": "on"
            },
            {
                "color": "#b4d59d"
            }
        ]
    },
    {
        "featureType": "landscape.natural",
        "elementType": "all",
        "stylers": [
            {
                "visibility": "simplified"
            },
            {
                "saturation": "-43"
            },
            {
                "lightness": "-10"
            },
            {
                "gamma": "3.59"
            }
        ]
    },
    {
        "featureType": "landscape.natural",
        "elementType": "geometry",
        "stylers": [
            {
                "hue": "#71ff00"
            },
            {
                "visibility": "on"
            },
            {
                "lightness": "-47"
            },
            {
                "saturation": "26"
            },
            {
                "gamma": "1.80"
            }
        ]
    },
    {
        "featureType": "landscape.natural.terrain",
        "elementType": "all",
        "stylers": [
            {
                "visibility": "simplified"
            },
            {
                "lightness": "-5"
            },
            {
                "saturation": "-35"
            },
            {
                "gamma": "2.12"
            }
        ]
    },
    {
        "featureType": "poi",
        "elementType": "all",
        "stylers": [
            {
                "visibility": "on"
            }
        ]
    },
    {
        "featureType": "poi",
        "elementType": "labels",
        "stylers": [
            {
                "visibility": "off"
            }
        ]
    },
    {
        "featureType": "road",
        "elementType": "labels.text.stroke",
        "stylers": [
            {
                "visibility": "off"
            }
        ]
    },
    {
        "featureType": "road.highway",
        "elementType": "geometry",
        "stylers": [
            {
                "color": "#c2db9b"
            }
        ]
    },
    {
        "featureType": "road.arterial",
        "elementType": "geometry",
        "stylers": [
            {
                "color": "#c2db9b"
            }
        ]
    },
    {
        "featureType": "road.local",
        "elementType": "geometry",
        "stylers": [
            {
                "color": "#b9d490"
            },
            {
                "lightness": 16
            },
            {
                "visibility": "on"
            }
        ]
    },
    {
        "featureType": "transit",
        "elementType": "geometry",
        "stylers": [
            {
                "color": "#9dbb70"
            },
            {
                "lightness": 19
            },
            {
                "visibility": "off"
            }
        ]
    },
    {
        "featureType": "transit",
        "elementType": "labels.text.stroke",
        "stylers": [
            {
                "visibility": "off"
            }
        ]
    },
    {
        "featureType": "transit.station.airport",
        "elementType": "geometry.fill",
        "stylers": [
            {
                "visibility": "off"
            }
        ]
    },
    {
        "featureType": "water",
        "elementType": "geometry",
        "stylers": [
            {
                "color": "#91ddf9"
            },
            {
                "lightness": 17
            }
        ]
    },
    {
        "featureType": "water",
        "elementType": "labels.text.stroke",
        "stylers": [
            {
                "visibility": "off"
            }
        ]
    }
]